zouti_utils/__init__.py
zouti_utils/database.py
zouti_utils/json.py
zouti_utils/model.py
zouti_utils-1.0.2.dist-info/LICENSE
zouti_utils-1.0.2.dist-info/METADATA
zouti_utils-1.0.2.dist-info/WHEEL
zouti_utils-1.0.2.dist-info/top_level.txt
zouti_utils-1.0.2.dist-info/RECORD
