Metadata-Version: 2.1
Name: zouti-utils
Version: 1.0.2
Summary: Database utilities for my projects
Author-email: ZoutigeWolf <guuskamphuis@gmail.com>
Classifier: Programming Language :: Python :: 3
Classifier: License :: OSI Approved :: MIT License
Classifier: Operating System :: OS Independent
Requires-Python: >=3.11
License-File: LICENSE
Requires-Dist: PyMySQL
